counter/counter.v
module counter (clock, reset, enable, counter_out);
input clock, reset, enable;
output [3:0] counter_out;
wire clock, reset, enable;
reg [3:0] counter_out ;
always @ (posedge clock)
if(reset) begin
counter_out <= #1 4'b0000;
end
else if(enable) begin
counter_out <= #1 counter_out+1;
end
endmodule

counter/counter_tb.v
`include "counter.v"
module counter_tb();
reg clock, reset, enable;
wire [3:0] counter_out;
integer i;
initial begin 
$dumpfile("waveform.vcd");
$dumpvars(0, counter_tb);	
$display("time\tclock\treset\tenable\tcounter_out");
$monitor("%g\t%b\t%b\t%b\t%b",$time, clock, reset, enable, counter_out);
clock=1;
reset=0;
enable=0;
#5 reset=1;
#10 reset=0;
#10 enable=1;
#200 enable=0;
#5 $finish;
end

always begin
#5 clock = !clock;
end

counter C0 (clock, reset, enable, counter_out);
endmodule

counter/waveform.vcd
$date
	Thu May 14 19:50:18 2020
$end
$version
	Icarus Verilog
$end
$timescale
	1s
$end
$scope module counter_tb $end
$var wire 4 ! counter_out [3:0] $end
$var reg 1 " clock $end
$var reg 1 # enable $end
$var reg 1 $ reset $end
$scope module C0 $end
$var wire 1 % clock $end
$var wire 1 & enable $end
$var wire 1 ' reset $end
$var reg 4 ( counter_out [3:0] $end
$upscope $end
$upscope $end
$enddefinitions $end
#0
$dumpvars
bx (
0'
0&
1%
0$
0#
1"
bx !
$end
#5
0"
0%
1$
1'
#10
1"
1%
#11
b0 (
b0 !
#15
0"
0%
0$
0'
#20
1"
1%
#25
0"
0%
1#
1&
#30
1"
1%
#31
b1 (
b1 !
#35
0"
0%
#40
1"
1%
#41
b10 (
b10 !
#45
0"
0%
#50
1"
1%
#51
b11 (
b11 !
#55
0"
0%
#60
1"
1%
#61
b100 (
b100 !
#65
0"
0%
#70
1"
1%
#71
b101 (
b101 !
#75
0"
0%
#80
1"
1%
#81
b110 (
b110 !
#85
0"
0%
#90
1"
1%
#91
b111 (
b111 !
#95
0"
0%
#100
1"
1%
#101
b1000 (
b1000 !
#105
0"
0%
#110
1"
1%
#111
b1001 (
b1001 !
#115
0"
0%
#120
1"
1%
#121
b1010 (
b1010 !
#125
0"
0%
#130
1"
1%
#131
b1011 (
b1011 !
#135
0"
0%
#140
1"
1%
#141
b1100 (
b1100 !
#145
0"
0%
#150
1"
1%
#151
b1101 (
b1101 !
#155
0"
0%
#160
1"
1%
#161
b1110 (
b1110 !
#165
0"
0%
#170
1"
1%
#171
b1111 (
b1111 !
#175
0"
0%
#180
1"
1%
#181
b0 (
b0 !
#185
0"
0%
#190
1"
1%
#191
b1 (
b1 !
#195
0"
0%
#200
1"
1%
#201
b10 (
b10 !
#205
0"
0%
#210
1"
1%
#211
b11 (
b11 !
#215
0"
0%
#220
1"
1%
#221
b100 (
b100 !
#225
0"
0%
0#
0&
